ghostipy/__init__.py
ghostipy/utils.py
ghostipy/version.py
ghostipy/dsp/__init__.py
ghostipy/dsp/analytic.py
ghostipy/dsp/convolution.py
ghostipy/dsp/filtering.py
ghostipy/dsp/firfilter.py
ghostipy/plotting/__init__.py
ghostipy/plotting/core.py
ghostipy/spectral/__init__.py
ghostipy/spectral/cwt.py
ghostipy/spectral/mtm.py
ghostipy/spectral/wavelets.py
ghostipy/spectral/wsst.py
ghostipy-0.2.2.dist-info/LICENSE
ghostipy-0.2.2.dist-info/METADATA
ghostipy-0.2.2.dist-info/WHEEL
ghostipy-0.2.2.dist-info/top_level.txt
ghostipy-0.2.2.dist-info/RECORD
