Metadata-Version: 2.1
Name: ghostipy
Version: 0.2.2
Summary: Signal processing and spectral analysis toolbox
Author: Joshua Chu
Author-email: jpc6@rice.edu
License: Apache License
Keywords: neuroscience spectral analysis
Platform: any
Classifier: Programming Language :: Python :: 3
License-File: LICENSE
Requires-Dist: numpy (>=1.18.1)
Requires-Dist: scipy (>=1.4.1)
Requires-Dist: pyfftw (>=0.12.0)
Requires-Dist: numba (>=0.48.0)
Requires-Dist: dask (>=2.15.0)
Requires-Dist: xarray (>=0.15.1)
Requires-Dist: matplotlib (>=3.1.3)
Requires-Dist: datashader (>=0.10.0)
Requires-Dist: hvplot (>=0.5.2)
